prettytoml/__init__.py
prettytoml/_version.py
prettytoml/errors.py
prettytoml/test_prettifier.py
prettytoml/test_util.py
prettytoml/util.py
prettytoml/elements/__init__.py
prettytoml/elements/abstracttable.py
prettytoml/elements/array.py
prettytoml/elements/atomic.py
prettytoml/elements/common.py
prettytoml/elements/errors.py
prettytoml/elements/factory.py
prettytoml/elements/inlinetable.py
prettytoml/elements/metadata.py
prettytoml/elements/table.py
prettytoml/elements/tableheader.py
prettytoml/elements/test_array.py
prettytoml/elements/test_atomic.py
prettytoml/elements/test_common.py
prettytoml/elements/test_factory.py
prettytoml/elements/test_inlinetable.py
prettytoml/elements/test_metadata.py
prettytoml/elements/test_table.py
prettytoml/elements/test_tableheader.py
prettytoml/elements/test_traversal.py
prettytoml/elements/traversal/__init__.py
prettytoml/elements/traversal/predicates.py
prettytoml/lexer/__init__.py
prettytoml/lexer/test_lexer.py
prettytoml/parser/__init__.py
prettytoml/parser/elementsanitizer.py
prettytoml/parser/errors.py
prettytoml/parser/parser.py
prettytoml/parser/recdesc.py
prettytoml/parser/test_parser.py
prettytoml/parser/tokenstream.py
prettytoml/prettifier/__init__.py
prettytoml/prettifier/commentspace.py
prettytoml/prettifier/common.py
prettytoml/prettifier/deindentanonymoustable.py
prettytoml/prettifier/linelength.py
prettytoml/prettifier/tableassignment.py
prettytoml/prettifier/tableentrysort.py
prettytoml/prettifier/tableindent.py
prettytoml/prettifier/tablesep.py
prettytoml/prettifier/test_commentspace.py
prettytoml/prettifier/test_deindentanonymoustable.py
prettytoml/prettifier/test_linelength.py
prettytoml/prettifier/test_tableassignment.py
prettytoml/prettifier/test_tableentrysort.py
prettytoml/prettifier/test_tableindent.py
prettytoml/prettifier/test_tablesep.py
prettytoml/tokens/__init__.py
prettytoml/tokens/errors.py
prettytoml/tokens/py2toml.py
prettytoml-0.3.dist-info/DESCRIPTION.rst
prettytoml-0.3.dist-info/METADATA
prettytoml-0.3.dist-info/RECORD
prettytoml-0.3.dist-info/WHEEL
prettytoml-0.3.dist-info/metadata.json
prettytoml-0.3.dist-info/top_level.txt
