Metadata-Version: 2.0
Name: prettytoml
Version: 0.3
Summary: TOML Prettifier for Python
Home-page: https://github.com/Jumpscale/python-prettytoml
Author: Amr Hassan
Author-email: amr.hassan@gmail.com
License: UNKNOWN
Keywords: toml
Platform: UNKNOWN
Classifier: Programming Language :: Python :: 2.7
Classifier: Programming Language :: Python :: 3.4
Classifier: Programming Language :: Python :: 3.5
Requires-Dist: iso8601
Requires-Dist: pytoml
Requires-Dist: pytz
Requires-Dist: six
Requires-Dist: strict-rfc3339
Requires-Dist: timestamp
